formsg/__init__.py
formsg/django.py
formsg/flask.py
formsg/utils.py
formsg-0.1.8.dist-info/LICENSE
formsg-0.1.8.dist-info/METADATA
formsg-0.1.8.dist-info/WHEEL
formsg-0.1.8.dist-info/RECORD
