Metadata-Version: 2.1
Name: formsg
Version: 0.1.8
Summary: A Python SDK for handling FormSG webhooks.
Author: 5 Health Inc
Author-email: engineers@botmd.io
Requires-Python: >=3.9,<4.0
Classifier: Programming Language :: Python :: 3
Classifier: Programming Language :: Python :: 3.9
Classifier: Programming Language :: Python :: 3.10
Classifier: Programming Language :: Python :: 3.11
Requires-Dist: pynacl (>=1.4.0)
Requires-Dist: requests
